cifparse/__init__.py
cifparse/main.py
cifparse/sections.py
cifparse/functions/__init__.py
cifparse/functions/field.py
cifparse/functions/record.py
cifparse/functions/records.py
cifparse/functions/sql.py
cifparse/records/__init__.py
cifparse/records/airport_gates.py
cifparse/records/airports.py
cifparse/records/airway_markers.py
cifparse/records/airway_points.py
cifparse/records/airway_restrictions.py
cifparse/records/alternate_records.py
cifparse/records/appl_table.py
cifparse/records/company_routes.py
cifparse/records/controlleds.py
cifparse/records/cruise_tables.py
cifparse/records/enroute_comms.py
cifparse/records/fir_uirs.py
cifparse/records/flight_plannings.py
cifparse/records/glss.py
cifparse/records/heli_msas.py
cifparse/records/heli_procedures.py
cifparse/records/heli_taas.py
cifparse/records/heli_terminal_comms.py
cifparse/records/heli_waypoints.py
cifparse/records/heliports.py
cifparse/records/holds.py
cifparse/records/loc_gss.py
cifparse/records/mlss.py
cifparse/records/moras.py
cifparse/records/msas.py
cifparse/records/ndb_navaids.py
cifparse/records/path_points.py
cifparse/records/preferred_routes.py
cifparse/records/procedures.py
cifparse/records/record_base.py
cifparse/records/reference_tables.py
cifparse/records/rest_type_table.py
cifparse/records/restriction_base.py
cifparse/records/restrictives.py
cifparse/records/runways.py
cifparse/records/taas.py
cifparse/records/table_base.py
cifparse/records/terminal_comms.py
cifparse/records/terminal_markers.py
cifparse/records/validity.py
cifparse/records/vhf_navaids.py
cifparse/records/waypoints.py
cifparse/records/airport/__init__.py
cifparse/records/airport/base.py
cifparse/records/airport/continuation.py
cifparse/records/airport/planning.py
cifparse/records/airport/planning_continuation.py
cifparse/records/airport/primary.py
cifparse/records/airport/widths.py
cifparse/records/airport_gate/__init__.py
cifparse/records/airport_gate/base.py
cifparse/records/airport_gate/continuation.py
cifparse-2.0.9.dist-info/licenses/LICENSE
cifparse-2.0.9.dist-info/METADATA
cifparse-2.0.9.dist-info/WHEEL
cifparse-2.0.9.dist-info/top_level.txt
cifparse-2.0.9.dist-info/RECORD
