Metadata-Version: 2.4
Name: cifparse
Version: 2.0.9
Summary: A python parser for the FAA CIFP
Author: misterrodg
License-Expression: GPL-3.0-only
Project-URL: Homepage, https://github.com/misterrodg/cifparse
Project-URL: Bug Tracker, https://github.com/misterrodg/cifparse/issues
Classifier: Programming Language :: Python :: 3
Classifier: Operating System :: OS Independent
Requires-Python: >=3.10
License-File: LICENSE
Dynamic: license-file
